robertcommonbasic/__init__.py
robertcommonbasic/basic/__init__.py
robertcommonbasic/basic/base/__init__.py
robertcommonbasic/basic/base/constant.py
robertcommonbasic/basic/cache/__init__.py
robertcommonbasic/basic/cache/utils.py
robertcommonbasic/basic/cls/__init__.py
robertcommonbasic/basic/cls/utils.py
robertcommonbasic/basic/data/__init__.py
robertcommonbasic/basic/data/conversion.py
robertcommonbasic/basic/data/crc16.py
robertcommonbasic/basic/data/csv.py
robertcommonbasic/basic/data/datatuple.py
robertcommonbasic/basic/data/express.py
robertcommonbasic/basic/data/frame.py
robertcommonbasic/basic/data/nametuple.py
robertcommonbasic/basic/data/type.py
robertcommonbasic/basic/data/utils.py
robertcommonbasic/basic/decorator/__init__.py
robertcommonbasic/basic/decorator/utils.py
robertcommonbasic/basic/dt/__init__.py
robertcommonbasic/basic/dt/schedule.py
robertcommonbasic/basic/dt/utils.py
robertcommonbasic/basic/encrypt/__init__.py
robertcommonbasic/basic/encrypt/aes.py
robertcommonbasic/basic/encrypt/dsa.py
robertcommonbasic/basic/encrypt/hash.py
robertcommonbasic/basic/encrypt/md5.py
robertcommonbasic/basic/encrypt/rsa.py
robertcommonbasic/basic/error/__init__.py
robertcommonbasic/basic/error/utils.py
robertcommonbasic/basic/exector/__init__.py
robertcommonbasic/basic/exector/utils.py
robertcommonbasic/basic/file/__init__.py
robertcommonbasic/basic/file/csv.py
robertcommonbasic/basic/file/ini.py
robertcommonbasic/basic/file/log.py
robertcommonbasic/basic/file/xml.py
robertcommonbasic/basic/file/yaml.py
robertcommonbasic/basic/file/zip.py
robertcommonbasic/basic/log/__init__.py
robertcommonbasic/basic/log/utils.py
robertcommonbasic/basic/log/watch.py
robertcommonbasic/basic/net/__init__.py
robertcommonbasic/basic/net/utils.py
robertcommonbasic/basic/os/__init__.py
robertcommonbasic/basic/os/cmd.py
robertcommonbasic/basic/os/env.py
robertcommonbasic/basic/os/file.py
robertcommonbasic/basic/os/path.py
robertcommonbasic/basic/process/__init__.py
RobertCommonBasic-0.1.66.dist-info/LICENSE
RobertCommonBasic-0.1.66.dist-info/METADATA
RobertCommonBasic-0.1.66.dist-info/WHEEL
RobertCommonBasic-0.1.66.dist-info/top_level.txt
RobertCommonBasic-0.1.66.dist-info/RECORD
