Metadata-Version: 2.1
Name: RobertCommonBasic
Version: 0.1.66
Summary: Robert Common Basic Library
Home-page: https://github.com/hun0423/RobertCommonBasic
Author: Robert0423
Author-email: 851010070@qq.com
License: MIT
Platform: UNKNOWN
Classifier: License :: OSI Approved :: MIT License
Classifier: Programming Language :: Python
Classifier: Programming Language :: Python :: 3
Classifier: Programming Language :: Python :: 3.6
Classifier: Programming Language :: Python :: Implementation :: CPython
Classifier: Programming Language :: Python :: Implementation :: PyPy
Requires-Python: >=3.6.0
License-File: LICENSE
Requires-Dist: chardet
Requires-Dist: colorama
Requires-Dist: cryptography
Requires-Dist: func-timeout
Requires-Dist: MarkupSafe
Requires-Dist: numpy
Requires-Dist: pandas
Requires-Dist: psutil
Requires-Dist: pycryptodome
Requires-Dist: pycryptodomex
Requires-Dist: pymongo
Requires-Dist: python-dateutil
Requires-Dist: pytz
Requires-Dist: pyzipper
Requires-Dist: simpleeval
Requires-Dist: six
Requires-Dist: xmltodict
Requires-Dist: tzlocal
